elgato_toggle-0.1.3.dist-info/METADATA
elgato_toggle-0.1.3.dist-info/WHEEL
elgato_toggle-0.1.3.dist-info/entry_points.txt
elgato_toggle/__init__.py
elgato_toggle/__main__.py
elgato_toggle-0.1.3.dist-info/RECORD
